{
  "composer_name": "Dietrich Buxtehude",
  "name_last_first": "Buxtehude, Dietrich",
  "slug": "buxtehude",
  "wiki_page": "https://en.wikipedia.org/wiki/Dietrich_Buxtehude",
  "apple_music_playlist": "https://music.apple.com/mk/playlist/pl.3c5d5fed669d4904a3c47b2b3367b3d5",
  "era": "Baroque",
  "dates": "1637 – 1707 (c.)",
  "nationality": "DNK/DEU",
  "notable": false,
  "works": [
    {
      "title": "'Der Herr ist mit mir' BuxWV15",
      "musicxml": "musicxml/Buxtehude_-_Alelluia.mxl",
      "midi": "midi/Buxtehude_-_Alelluia.mid",
      "time_signature": "3/4",
      "instruments": [
        "Violin",
        "Violoncello",
        "Soprano",
        "Alto",
        "Tenor",
        "Bass",
        "Pipe Organ"
      ],
      "tempo_markings": [
        "Adagio"
      ],
      "is_multi_movement": false,
      "pdmx": {
        "rating": 0.0,
        "n_favorites": 0,
        "n_views": 61,
        "duration_seconds": 179.15543423592862,
        "n_notes": 2060,
        "complexity": "0",
        "is_original": false,
        "is_best_arrangement": true,
        "genres": "classical",
        "tags": "chorus-sacredchorus",
        "musescore_url": "https://musescore.com/user/4810366/scores/6271976",
        "musescore_duration": "03"
      },
      "key": "E♭ major",
      "instruments_gm": [
        "Violin",
        "Cello",
        "Choir Aahs",
        "Church Organ"
      ],
      "tempo_bpm": 71,
      "n_measures": 58,
      "n_parts": 8,
      "n_notes": 2057,
      "notes_per_second": 11.5,
      "apple_music_search_query": "Buxtehude E♭ major 'Der Herr ist mit mir' BuxWV15",
      "parent_work_title": "alleluia",
      "wikidata_id": "Q932247",
      "wikidata_title": "Der Herr ist mit mir",
      "musicbrainz_id": "97f67495-b59d-4dcf-8067-a02d810762f2",
      "imslp_id": "Der_Herr_ist_mit_mir,_BuxWV_15_(Buxtehude,_Dietrich)",
      "wikidata_match_method": "catalog_extracted",
      "apple_music_classical_search_url": "https://classical.music.apple.com/us/search?q=Buxtehude%20%27Der%20Herr%20ist%20mit%20mir%27%20BuxWV15",
      "display_title": "Der Herr ist mit mir"
    },
    {
      "title": "Buxtehude - Passacaglia in D Minor. BuxWV 161. {Professional production score.}",
      "musicxml": "musicxml/Buxtehude_-_Passacaglia_in_D_Minor_BuxWV_161_Professional_production_score.mxl",
      "midi": "midi/Buxtehude_-_Passacaglia_in_D_Minor_BuxWV_161_Professional_production_score.mid",
      "form": "Passacaglia",
      "time_signature": "3/2",
      "instruments": [
        "Organ"
      ],
      "is_multi_movement": false,
      "pdmx": {
        "rating": 4.83,
        "n_favorites": 51,
        "n_views": 1050,
        "duration_seconds": 1376.9108022764865,
        "n_notes": 2042,
        "complexity": "0",
        "is_original": false,
        "is_best_arrangement": true,
        "genres": "classical",
        "tags": "dietrichbuxtehude-passcaglia-dminor-bach-buxtehude-dietrich-counterpoint-organ-pipe-pipeorgan-bach-beethoven-mozart-baroque-dminor-minor-d",
        "musescore_url": "https://musescore.com/tsar_mandelstamdavid_is_a_retarded_cuck/scores/5135608",
        "musescore_duration": "05:46"
      },
      "key": "D Minor",
      "instruments_gm": [
        "Church Organ"
      ],
      "tempo_bpm": 120,
      "n_measures": 123,
      "n_parts": 1,
      "n_notes": 1938,
      "notes_per_second": 1.4,
      "apple_music_search_query": "Buxtehude D minor Buxtehude - Passacaglia in D Minor. BuxWV 161. {Pr",
      "parent_work_title": "Buxtehude - Passcagalia in D Minor.",
      "wikidata_id": "Q2310616",
      "wikidata_title": "Passacaglia in D minor",
      "musicbrainz_id": "8d42003f-8903-3a04-a0d1-369ab69a6423",
      "imslp_id": "Passacaglia_in_D_minor,_BuxWV_161_(Buxtehude,_Dietrich)",
      "wikidata_match_method": "catalog_extracted",
      "apple_music_classical_search_url": "https://classical.music.apple.com/us/search?q=Buxtehude%20-%20Passacaglia%20in%20D%20Minor.%20BuxWV%20161.%20%7BProfessional",
      "display_title": "Passacaglia in D minor"
    }
  ],
  "birth_year": 1637,
  "death_year": 1707,
  "catalog_type": "BuxWV",
  "wikipedia_extract": "Danish-German organist and composer, the most important organist-composer of the generation before J.S. Bach (who walked 250 miles to hear him play). Known for organ preludes, chorale settings, and sacred vocal works.",
  "wikidata_id": "Q153637"
}