{
  "composer_name": "Arvo Pärt",
  "name_last_first": "Pärt, Arvo",
  "slug": "part",
  "wiki_page": "https://en.wikipedia.org/wiki/Arvo_Pärt",
  "apple_music_playlist": "https://music.apple.com/mk/playlist/pl.fe709e9068f14dea876e6015c4b0ff4f",
  "era": "Contemporary",
  "dates": "1935 –",
  "nationality": "EST",
  "notable": true,
  "works": [
    {
      "title": "Pari Intervallo",
      "musicxml": "musicxml/Pari_Intervallo.mxl",
      "midi": "midi/Pari_Intervallo.mid",
      "instruments": [
        "Pipe Organ"
      ],
      "is_multi_movement": false,
      "pdmx": {
        "rating": 4.6,
        "n_favorites": 33,
        "n_views": 3229,
        "duration_seconds": 591.9999999842133,
        "n_notes": 440,
        "complexity": "0",
        "is_original": false,
        "is_best_arrangement": true,
        "genres": "classical",
        "tags": "NA",
        "musescore_url": "https://musescore.com/user/27989190/scores/5424967",
        "musescore_duration": "04:56"
      },
      "key": "G♭ major",
      "instruments_gm": [
        "Church Organ"
      ],
      "tempo_bpm": 60,
      "n_measures": 74,
      "n_parts": 1,
      "n_notes": 292,
      "notes_per_second": 0.5,
      "apple_music_search_query": "Pärt G♭ major Pari Intervallo",
      "year_composed": 1976,
      "wikidata_id": "Q3365062",
      "wikidata_title": "Pari intervallo",
      "musicbrainz_id": "88dbd42f-5466-486a-bf16-5f0dc817a36e",
      "wikidata_match_method": "title_exact",
      "apple_music_classical_search_url": "https://classical.music.apple.com/us/search?q=P%C3%A4rt%20Pari%20Intervallo",
      "display_title": "Pari intervallo"
    }
  ],
  "birth_year": 1935,
  "wikipedia_extract": "Arvo Pärt (Estonian pronunciation: [ˈɑrvo ˈpært]; born 11 September 1935) is an Estonian composer of contemporary classical music. Since the late 1970s, Pärt has worked in a minimalist style that employs tintinnabuli, a compositional technique he invented. Pärt's music is in part inspired by Gregorian chant.",
  "wikipedia_compositions_url": "https://en.wikipedia.org/wiki/List_of_compositions_by_Arvo_P%C3%A4rt",
  "wikidata_id": "Q189534",
  "apple_music_artist_id": "2601882",
  "apple_music_classical_url": "https://classical.music.apple.com/us/artist/2601882"
}